ao/__init__.py
ao/cli/__init__.py
ao/cli/ao_config.py
ao/cli/ao_record.py
ao/cli/ao_server.py
ao/common/__init__.py
ao/common/config.py
ao/common/constants.py
ao/common/logger.py
ao/common/utils.py
ao/runner/__init__.py
ao/runner/agent_runner.py
ao/runner/context_manager.py
ao/runner/string_matching.py
ao/runner/monkey_patching/__init__.py
ao/runner/monkey_patching/api_parser.py
ao/runner/monkey_patching/apply_monkey_patches.py
ao/runner/monkey_patching/patching_utils.py
ao/runner/monkey_patching/api_parsers/__init__.py
ao/runner/monkey_patching/api_parsers/genai_api_parser.py
ao/runner/monkey_patching/api_parsers/httpx_api_parser.py
ao/runner/monkey_patching/api_parsers/mcp_api_parser.py
ao/runner/monkey_patching/api_parsers/requests_api_parser.py
ao/runner/monkey_patching/patches/__init__.py
ao/runner/monkey_patching/patches/genai_patch.py
ao/runner/monkey_patching/patches/httpx_patch.py
ao/runner/monkey_patching/patches/mcp_patches.py
ao/runner/monkey_patching/patches/randomness_patch.py
ao/runner/monkey_patching/patches/requests_patch.py
ao/server/__init__.py
ao/server/database_manager.py
ao/server/file_watcher.py
ao/server/main_server.py
ao/server/database_backends/__init__.py
ao/server/database_backends/postgres.py
ao/server/database_backends/sqlite.py
ao_dev-0.0.7.dist-info/licenses/LICENSE
ao_dev-0.0.7.dist-info/METADATA
ao_dev-0.0.7.dist-info/WHEEL
ao_dev-0.0.7.dist-info/entry_points.txt
ao_dev-0.0.7.dist-info/top_level.txt
ao_dev-0.0.7.dist-info/RECORD
