Metadata-Version: 2.4
Name: ao-dev
Version: 0.0.7
Summary: A development tool for LLM call visualization and debugging
Requires-Python: >=3.10
License-File: LICENSE
Requires-Dist: pyyaml
Requires-Dist: dill
Requires-Dist: debugpy
Requires-Dist: psutil
Requires-Dist: psycopg2-binary
Requires-Dist: python-dotenv
Requires-Dist: fastapi
Requires-Dist: flatten_dict
Requires-Dist: flatten_json
Provides-Extra: dev
Requires-Dist: black==25.1.0; extra == "dev"
Requires-Dist: pytest; extra == "dev"
Requires-Dist: pre-commit; extra == "dev"
Requires-Dist: responses; extra == "dev"
Requires-Dist: openai; extra == "dev"
Requires-Dist: anthropic; extra == "dev"
Requires-Dist: openai-agents; extra == "dev"
Requires-Dist: google-genai; extra == "dev"
Requires-Dist: hydra-core; extra == "dev"
Requires-Dist: e2b_code_interpreter; extra == "dev"
Requires-Dist: together; extra == "dev"
Requires-Dist: langchain; extra == "dev"
Requires-Dist: langchain-anthropic; extra == "dev"
Requires-Dist: langchain-openai; extra == "dev"
Provides-Extra: examples
Requires-Dist: openai; extra == "examples"
Requires-Dist: anthropic; extra == "examples"
Requires-Dist: openai-agents; extra == "examples"
Requires-Dist: google-genai; extra == "examples"
Provides-Extra: docs
Requires-Dist: mkdocs-material>=9.5; extra == "docs"
Requires-Dist: mkdocs-minify-plugin; extra == "docs"
Requires-Dist: mkdocstrings[python]>=0.24; extra == "docs"
Dynamic: license-file
